pebbling/__init__.py
pebbling/settings.py
pebbling/version.py
pebbling/common/__init__.py
pebbling/common/models.py
pebbling/common/protocol/__init__.py
pebbling/common/protocol/types.py
pebbling/observability/__init__.py
pebbling/observability/openinference.py
pebbling/penguin/__init__.py
pebbling/penguin/manifest.py
pebbling/penguin/pebblify.py
pebbling/security/__init__.py
pebbling/security/agent_identity.py
pebbling/security/common/__init__.py
pebbling/security/common/keys.py
pebbling/security/did/__init__.py
pebbling/security/did/document.py
pebbling/security/did/manager.py
pebbling/server/__init__.py
pebbling/server/applications.py
pebbling/server/task_manager.py
pebbling/server/scheduler/__init__.py
pebbling/server/scheduler/base.py
pebbling/server/scheduler/memory_scheduler.py
pebbling/server/scheduler/redis_scheduler.py
pebbling/server/static/agent.html
pebbling/server/static/chat.html
pebbling/server/static/common.css
pebbling/server/static/common.js
pebbling/server/static/storage.html
pebbling/server/storage/__init__.py
pebbling/server/storage/base.py
pebbling/server/storage/memory_storage.py
pebbling/server/storage/postgres_storage.py
pebbling/server/storage/qdrant_storage.py
pebbling/server/utils/display.py
pebbling/server/workers/__init__.py
pebbling/server/workers/base.py
pebbling/server/workers/manifest_worker.py
pebbling/utils/__init__.py
pebbling/utils/cert_helper.py
pebbling/utils/constants.py
pebbling/utils/logging.py
pebbling/utils/task_telemetry.py
pebbling/utils/worker_utils.py
pebbling-0.1.1.dist-info/METADATA
pebbling-0.1.1.dist-info/WHEEL
pebbling-0.1.1.dist-info/RECORD
