Metadata-Version: 2.4
Name: pebbling
Version: 0.1.1
Summary: A protocol framework for agent-to-agent communication
Author-email: Rahul Dutta <raahul@pebbling.ai>
License: MIT
Classifier: License :: OSI Approved :: MIT License
Classifier: Operating System :: OS Independent
Classifier: Programming Language :: Python :: 3
Requires-Python: >=3.12
Requires-Dist: aiofiles>=24.1.0
Requires-Dist: cryptography>=44.0.2
Requires-Dist: didkit>=0.3.3
Requires-Dist: loguru>=0.7.3
Requires-Dist: opentelemetry-api>=1.35.0
Requires-Dist: opentelemetry-exporter-otlp-proto-http>=1.35.0
Requires-Dist: opentelemetry-exporter-otlp>=1.35.0
Requires-Dist: opentelemetry-instrumentation-fastapi>=0.56b0
Requires-Dist: opentelemetry-instrumentation-httpx>=0.56b0
Requires-Dist: opentelemetry-sdk>=1.35.0
Requires-Dist: orjson>=3.10.18
Requires-Dist: pipreqs>=0.5.0
Requires-Dist: psycopg2-binary>=2.9.10
Requires-Dist: pydantic>=1.8.2
Requires-Dist: pyyaml>=6.0.2
Requires-Dist: redis>=6.4.0
Requires-Dist: rich>=13.0.0
Requires-Dist: sqlalchemy>=2.0.43
Requires-Dist: starlette>=0.48.0
Requires-Dist: twine>=6.1.0
Requires-Dist: types-requests>=2.32.0.20250328
Requires-Dist: uvicorn>=0.15.0
Requires-Dist: uvx<2.0
Provides-Extra: dev
Requires-Dist: pytest-asyncio>=0.26.0; extra == 'dev'
